qaiko/__init__.py
qaiko/main.py
qaiko-0.1.0.dist-info/licenses/LICENCE
qaiko-0.1.0.dist-info/METADATA
qaiko-0.1.0.dist-info/WHEEL
qaiko-0.1.0.dist-info/entry_points.txt
qaiko-0.1.0.dist-info/top_level.txt
qaiko-0.1.0.dist-info/RECORD
