Metadata-Version: 2.4
Name: qaiko
Version: 0.1.0
Summary: A simple example package
Author-email: Amol Deshmukh <amoldeshmukh@gmail.com>
License: MIT
Project-URL: Homepage, https://github.com/des137/qaiko
Project-URL: Repository, https://github.com/des137/qaiko
Classifier: Programming Language :: Python :: 3
Classifier: License :: OSI Approved :: MIT License
Classifier: Operating System :: OS Independent
Requires-Python: >=3.8
License-File: LICENCE
Dynamic: license-file
